{"326588":{"hotelName":"Hotel One Taichung","hotelNameUtf8":"Hotel One Taichung","countryName":"Taiwan","countryCode":"TW","cityName":"Taichung","thImgUrl":"http:\/\/www.tnetnoc.com\/hotelphotos\/588\/326588\/2241284-Hotel-One-Taichung-Hotel-Exterior-1-LP.jpg","blackOutDates":null,"currency":"AUD","curySymbole":"$","promoCode":"PO","shortMarketingText":"Save 41% Per Night","offerAmount":"41","reviewerScore":"60","likes":"80%","userRating":"5","starRating":"5","hotelType":null,"bestFor":null,"sortOrder":"90","facilities":"Gym,Pool","facilitiesText":"Spa","price":"203","travelText":"save","hotelId":"326588","marketText":"Save 41% Per Night","isMemberExclusive":"0","isPromocodeApplicable":"value","promotion":[{"PO":{"50":"Book 30 Days In Advance & Save 50%"}}]},"331267":{"hotelName":"Tango Hotel Taichung","hotelNameUtf8":"Tango Hotel Taichung","countryName":"Taiwan","countryCode":"TW","cityName":"Taichung","thImgUrl":"http:\/\/www.tnetnoc.com\/hotelphotos\/267\/331267\/2631759-Tango-Hotel-Taichung-Lobby-3-LP.jpg","blackOutDates":null,"currency":"AUD","curySymbole":"$","promoCode":"PO","shortMarketingText":"Book 14 Days In Advance & Save 42% on Sat","offerAmount":"42","reviewerScore":"60","likes":"80%","userRating":"4","starRating":"4","hotelType":null,"bestFor":null,"sortOrder":85,"facilities":"Gym,Pool","facilitiesText":"Spa","price":"151","travelText":"save","hotelId":"331267","marketText":"Book 14 Days In Advance & Save 42% on Sat","isMemberExclusive":"0","isPromocodeApplicable":"value","promotion":[{"PO":{"50":"Stay 2 Nights & Save 50%"},"VA":["FREE Round Way Shuttle Bus to Railway"]}]},"1164421":{"hotelName":"Royal Seasons Hotel Taichung","hotelNameUtf8":"Royal Seasons Hotel Taichung","countryName":"Taiwan","countryCode":"TW","cityName":"Taichung","thImgUrl":"http:\/\/www.tnetnoc.com\/hotelphotos\/421\/1164421\/2241284-Royal-Seasons-Hotel-Taichung-Hotel-Exterior-1-LP.jpg","blackOutDates":null,"currency":"AUD","curySymbole":"$","promoCode":"PO","shortMarketingText":"Book 21 Days In Advance & Save 55%","offerAmount":"55","reviewerScore":"60","likes":"80%","userRating":"3","starRating":"3","hotelType":null,"bestFor":null,"sortOrder":80,"facilities":"Gym,Pool","facilitiesText":"Spa","price":"95","travelText":"save","hotelId":"1164421","marketText":"Book 21 Days In Advance & Save 55%","isMemberExclusive":"0","isPromocodeApplicable":"value","promotion":[{"PO":{"60":"Hotel Deal - Save 60% Per Night"},"VA":["Free Daily Breakfast & Internet Access"]}]},"327593":{"hotelName":"Evergreen Laurel Hotel Taichung","hotelNameUtf8":"Evergreen Laurel Hotel Taichung","countryName":"Taiwan","countryCode":"TW","cityName":"Taichung","thImgUrl":"http:\/\/www.tnetnoc.com\/hotelphotos\/593\/327593\/2631759-Evergreen-Laurel-Hotel-Taichung-Hotel-Exterior-1-LP.jpg","blackOutDates":null,"currency":"AUD","curySymbole":"$","promoCode":"PO","shortMarketingText":"Stay 4 Nights & Save 25%","offerAmount":"25","reviewerScore":"60","likes":"80%","userRating":"5","starRating":"5","hotelType":null,"bestFor":null,"sortOrder":75,"facilities":"Gym,Pool","facilitiesText":"Spa","price":"123","travelText":"save","hotelId":"327593","marketText":"Stay 4 Nights & Save 25%","isMemberExclusive":"0","isPromocodeApplicable":"value","promotion":[{"PO":{"25":"Hotel Deal - Save 25% Per Night"},"VA":["FREE Daily Breakfast & Internet Access"]}]},"973851":{"hotelName":"CityInn Plus Hotel Taichung","hotelNameUtf8":"CityInn Plus Hotel Taichung","countryName":"Taiwan","countryCode":"TW","cityName":"Taichung","thImgUrl":"http:\/\/www.tnetnoc.com\/hotelphotos\/851\/973851\/2631759-CityInn-Plus-Hotel-Taichung-Hotel-Exterior-2-LP.jpg","blackOutDates":null,"currency":"AUD","curySymbole":"$","promoCode":"PO","shortMarketingText":"Book 14 Days In Advance & Save 48% on Sun - Fri","offerAmount":"48","reviewerScore":"60","likes":"80%","userRating":"3","starRating":"3","hotelType":null,"bestFor":null,"sortOrder":"62","facilities":"Gym,Pool","facilitiesText":"Spa","price":"72","travelText":"save","hotelId":"973851","marketText":"Book 14 Days In Advance & Save 48% on Sun - Fri","isMemberExclusive":"0","isPromocodeApplicable":"value","promotion":[{"PO":{"52":"Stay 2 Nights & Save 52%"}}]},"350807":{"hotelName":"52 Hotel Taichung","hotelNameUtf8":"52 Hotel Taichung","countryName":"Taiwan","countryCode":"TW","cityName":"Taichung","thImgUrl":"http:\/\/www.tnetnoc.com\/hotelphotos\/807\/350807\/2241284-52-Hotel-Taichung-Hotel-Exterior-6-LP.jpg","blackOutDates":null,"currency":"AUD","curySymbole":"$","promoCode":"PO","shortMarketingText":"Jun Sale - Save 10% Per Night","offerAmount":"10","reviewerScore":"60","likes":"80%","userRating":"4","starRating":"4","hotelType":null,"bestFor":null,"sortOrder":75,"facilities":"Gym,Pool","facilitiesText":"Spa","price":"63","travelText":"save","hotelId":"350807","marketText":"Jun Sale - Save 10% Per Night","isMemberExclusive":"0","isPromocodeApplicable":"value","promotion":[{"PO":{"30":"Save 30% w\/ Free Upgrade & Lounge Use"},"VA":["Executive Room Facilities","Special Room Only Promotion"]}]},"322866":{"hotelName":"Hung's Mansion Hotel Taichung","hotelNameUtf8":"Hung's Mansion Hotel Taichung","countryName":"Taiwan","countryCode":"TW","cityName":"Taichung","thImgUrl":"http:\/\/www.tnetnoc.com\/hotelphotos\/866\/322866\/2631759-Hungs-Mansion-Hotel-Taichung-Fitness-Center-1-LP.jpg","blackOutDates":null,"currency":"AUD","curySymbole":"$","promoCode":"PO","shortMarketingText":"Book 14 Days In Advance & Save 10%","offerAmount":"10","reviewerScore":"60","likes":"80%","userRating":"4","starRating":"4","hotelType":null,"bestFor":null,"sortOrder":"35","facilities":"Gym,Pool","facilitiesText":"Spa","price":"125","travelText":"save","hotelId":"322866","marketText":"Book 14 Days In Advance & Save 10%","isMemberExclusive":"0","isPromocodeApplicable":"value","promotion":[{"PO":{"10":"Stay 2 Nights & Save 10%"}}]},"1070511":{"hotelName":"53 Hotel Taichung","hotelNameUtf8":"53 Hotel Taichung","countryName":"Taiwan","countryCode":"TW","cityName":"Taichung","thImgUrl":"http:\/\/www.tnetnoc.com\/hotelphotos\/511\/1070511\/2241284-53-Hotel-Taichung-Hotel-Exterior-1-LP.jpg","blackOutDates":null,"currency":"AUD","curySymbole":"$","promoCode":"PO","shortMarketingText":"Save 10% Per Night Included Breakfast & Internet","offerAmount":"10","reviewerScore":"60","likes":"80%","userRating":"4","starRating":"4","hotelType":null,"bestFor":null,"sortOrder":"35","facilities":"Gym,Pool","facilitiesText":"Spa","price":"86","travelText":"save","hotelId":"1070511","marketText":"Save 10% Per Night Included Breakfast & Internet","isMemberExclusive":"0","isPromocodeApplicable":"value","promotion":[{"PO":{"10":"Save 10% Per Night Included Breakfast & Internet"}}]},"340019":{"hotelName":"Le Parker Hotel Taichung","hotelNameUtf8":"Le Parker Hotel Taichung","countryName":"Taiwan","countryCode":"TW","cityName":"Taichung","thImgUrl":"http:\/\/www.tnetnoc.com\/hotelphotos\/019\/340019\/2241284-Le-Parker-Hotel-Taichung-Hotel-Exterior-1-LP.jpg","blackOutDates":null,"currency":"AUD","curySymbole":"$","promoCode":"PO","shortMarketingText":"Book 30 Days In Advance & Save 15% on Sun - Fri","offerAmount":"15","reviewerScore":"60","likes":"80%","userRating":"3","starRating":"3","hotelType":null,"bestFor":null,"sortOrder":"25","facilities":"Gym,Pool","facilitiesText":"Spa","price":"74","travelText":"save","hotelId":"340019","marketText":"Book 30 Days In Advance & Save 15% on Sun - Fri","isMemberExclusive":"0","isPromocodeApplicable":"value","promotion":[{"PO":{"15":"Book 30 Days In Advance & Save 15% on Sun - Fri"}}]}}